{
  "address": "atonevaloper1trmnr6hqu5v50xr0s8e3wu4xqkl68yrsa3tnm4",
  "moniker": "NexuSecurus",
  "identity": "D9211330D088E351",
  "description": "NexuSecurus started as a small team of blockchain enthusiasts and IT professionals with 10+ years in crypto our mission is to simplify blockchain for everyone setting up the required infrastructure, tools and resources to enable our users a better way to be part of DeFi.",
  "website": "https://nexusecurus.com",
  "security_contact": "atomone@nexusecurus.com"
}